benchstats/__init__.py
benchstats/__main__.py
benchstats/cli_parser.py
benchstats/common.py
benchstats/compare.py
benchstats/parser_GbenchJson.py
benchstats/parsers.py
benchstats/qbench.py
benchstats/render.py
benchstats-3.0.0.post1.dist-info/licenses/LICENSE
benchstats-3.0.0.post1.dist-info/METADATA
benchstats-3.0.0.post1.dist-info/WHEEL
benchstats-3.0.0.post1.dist-info/entry_points.txt
benchstats-3.0.0.post1.dist-info/top_level.txt
benchstats-3.0.0.post1.dist-info/RECORD
