Metadata-Version: 2.4
Name: benchstats
Version: 3.0.0.post1
Summary: Statistical Testing for Benchmark Results Comparison
Author-email: Aleksei Rechinskii <5dpea9nhd@mozmail.com>
License-Expression: MIT
Project-URL: Homepage, https://github.com/Arech/benchstats
Project-URL: Source, https://github.com/Arech/benchstats
Project-URL: Changelog, https://github.com/Arech/benchstats/blob/main/CHANGELOG.md
Project-URL: Bugtracker, https://github.com/Arech/benchstats/issues
Keywords: benchmarks,statistics,reports,analysis,optimization,performance,benchmarking,statistical analysis,brunner munzel,mann whitney u
Classifier: Programming Language :: Python
Classifier: Programming Language :: Python :: 3
Classifier: Programming Language :: Python :: 3.10
Classifier: Programming Language :: Python :: 3.11
Classifier: Programming Language :: Python :: 3.12
Classifier: Programming Language :: Python :: 3.13
Classifier: Programming Language :: Python :: 3.14
Classifier: Development Status :: 5 - Production/Stable
Classifier: Intended Audience :: Developers
Classifier: Intended Audience :: Information Technology
Classifier: Intended Audience :: Science/Research
Classifier: Operating System :: OS Independent
Classifier: Topic :: Scientific/Engineering
Classifier: Topic :: Scientific/Engineering :: Information Analysis
Classifier: Topic :: Software Development
Classifier: Topic :: System :: Benchmark
Classifier: Topic :: Utilities
Requires-Python: >=3.10
License-File: LICENSE
Requires-Dist: rich
Requires-Dist: numpy
Requires-Dist: scipy
Dynamic: license-file
